app/__init__.py
app/main.py
loopsniff-0.1.2.dist-info/entry_points.txt
loopsniff-0.1.2.dist-info/LICENSE
loopsniff-0.1.2.dist-info/METADATA
loopsniff-0.1.2.dist-info/WHEEL
loopsniff-0.1.2.dist-info/RECORD
