Metadata-Version: 2.3
Name: loopsniff
Version: 0.1.2
Summary: A static analysis tool for detecting inefficient SQLAlchemy loops
License: MIT
Author: Jiri Otoupal
Author-email: jiri-otoupal@ips-database.eu
Requires-Python: >=3.10
Classifier: License :: OSI Approved :: MIT License
Classifier: Programming Language :: Python :: 3
Classifier: Programming Language :: Python :: 3.10
Classifier: Programming Language :: Python :: 3.11
Classifier: Programming Language :: Python :: 3.12
Classifier: Programming Language :: Python :: 3.13
Requires-Dist: click (>=8.1.8,<9.0.0)
Requires-Dist: rich (>=13.9.4,<14.0.0)
